lr_logger.py
lr_logger-0.1.6.dist-info/METADATA
lr_logger-0.1.6.dist-info/WHEEL
lr_logger-0.1.6.dist-info/RECORD
