Metadata-Version: 2.1
Name: lr_logger
Version: 0.1.6
Summary: 
Author: Çağdaş Öztürk
Author-email: cagdas@littlerocket.nl
Requires-Python: >=3.10,<4.0
Classifier: Programming Language :: Python :: 3
Classifier: Programming Language :: Python :: 3.10
Classifier: Programming Language :: Python :: 3.11
Classifier: Programming Language :: Python :: 3.12
Requires-Dist: requests (>=2.32.3,<3.0.0)
